[
    {
        "content": [
            {
                "cat1": "Number", 
                "cat2": "Fraction", 
                "cat3": "", 
                "cat4": "", 
                "charcode": "0xa830", 
                "description": "", 
                "title": "NORTH INDIC FRACTION ONE QUARTER"
            }, 
            {
                "cat1": "Number", 
                "cat2": "Fraction", 
                "cat3": "", 
                "cat4": "", 
                "charcode": "0xa831", 
                "description": "", 
                "title": "NORTH INDIC FRACTION ONE HALF"
            }, 
            {
                "cat1": "Number", 
                "cat2": "Fraction", 
                "cat3": "", 
                "cat4": "", 
                "charcode": "0xa832", 
                "description": "", 
                "title": "NORTH INDIC FRACTION THREE QUARTERS"
            }, 
            {
                "cat1": "Number", 
                "cat2": "Fraction", 
                "cat3": "", 
                "cat4": "", 
                "charcode": "0xa833", 
                "description": "", 
                "title": "NORTH INDIC FRACTION ONE SIXTEENTH"
            }, 
            {
                "cat1": "Number", 
                "cat2": "Fraction", 
                "cat3": "", 
                "cat4": "", 
                "charcode": "0xa834", 
                "description": "", 
                "title": "NORTH INDIC FRACTION ONE EIGHTH"
            }, 
            {
                "cat1": "Number", 
                "cat2": "Fraction", 
                "cat3": "", 
                "cat4": "", 
                "charcode": "0xa835", 
                "description": "", 
                "title": "NORTH INDIC FRACTION THREE SIXTEENTHS"
            }, 
            {
                "cat1": "Symbol", 
                "cat2": "", 
                "cat3": "", 
                "cat4": "", 
                "charcode": "0xa836", 
                "description": "", 
                "title": "NORTH INDIC QUARTER MARK"
            }, 
            {
                "cat1": "Symbol", 
                "cat2": "", 
                "cat3": "", 
                "cat4": "", 
                "charcode": "0xa837", 
                "description": "", 
                "title": "NORTH INDIC PLACEHOLDER MARK"
            }, 
            {
                "cat1": "Symbol", 
                "cat2": "Currency", 
                "cat3": "", 
                "cat4": "", 
                "charcode": "0xa838", 
                "description": "", 
                "title": "NORTH INDIC RUPEE MARK"
            }, 
            {
                "cat1": "Symbol", 
                "cat2": "", 
                "cat3": "", 
                "cat4": "", 
                "charcode": "0xa839", 
                "description": "", 
                "title": "NORTH INDIC QUANTITY MARK"
            }
        ], 
        "name": "Common Indic Number Forms"
    }
]